{
    "allemand": { "name": "Allemand", "det": "d'", "color": "#FF9F6B" },
    "allemand lv2": { "name": "Allemand LV2", "det": "d'", "color": "#FF9F6B" },
    "allemand lv1": { "name": "Allemand LV1", "det": "d'", "color": "#FF9F6B" },
    "allemand lv3": { "name": "Allemand LV3", "det": "d'", "color": "#FF9F6B" },
    "anglais": { "name": "Anglais", "det": "d'", "color": "#FF9F6B" },
    "anglais lv1": { "name": "Anglais LV1", "det": "d'", "color": "#FF9F6B" },
    "anglais lv2": { "name": "Anglais LV2", "det": "d'", "color": "#FF9F6B" },
    "anglais lv3": { "name": "Anglais LV3", "det": "d'", "color": "#FF9F6B" },
    "anglais lv section": { "name": "Anglais Euro", "det": "d'", "color": "#FF9F6B" },
    "espagnol": { "name": "Espagnol", "det": "d'", "color": "#FF9F6B" },
    "espagnol lv1": { "name": "Espagnol LV1", "det": "d'", "color": "#FF9F6B" },
    "espagnol lv2": { "name": "Espagnol LV2", "det": "d'", "color": "#FF9F6B" },
    "espagnol lv3": { "name": "Espagnol LV3", "det": "d'", "color": "#FF9F6B" },

    "francais": { "name": "Français", "det": "de", "color": "#7FBFC3" },
    "culture gene.et expr": { "name": "Culture Générale et Expression", "det": "de", "color": "#7FBFC3" },
    "human.litter.philo": { "name": "Humanités, Littérature & Philosophie", "det": "d'", "color": "#7FBFC3" },
    "philosophie": { "name": "Philosophie", "det": "de", "color": "#7FBFC3" },

    "histoire geo": { "name": "Histoire-Géo", "det": "d'", "color": "#C6A0C8" },
    "histoire-geo": { "name": "Histoire-Géo", "det": "d'", "color": "#C6A0C8" },
    "histoire & geograph.": { "name": "Histoire-Géo", "det": "d'", "color": "#C6A0C8" },
    "histoire-geographie": { "name": "Histoire-Géographie", "det": "d'", "color": "#C6A0C8" },
    "ens. moral & civique": { "name": "Enseignement Moral et Civique", "det": "d'", "color": "#C6A0C8" },
    "education civique": { "name": "Éducation Civique", "det": "d'", "color": "#C6A0C8" },
    "sc.econo & sociales": { "name": "SES", "det": "de", "color": "#C6A0C8" },
    "sciences economiques et sociales": { "name": "SES", "det": "de", "color": "#C6A0C8" },

    "mathematiques": { "name": "Mathématiques", "det": "de", "color": "#8FB4DA" },
    "math 1ere": { "name": "Mathématiques 1ère", "det": "de", "color": "#8FB4DA" },
    "maths pour informatq": { "name": "Mathématiques pour l’informatique", "det": "de", "color": "#8FB4DA" },

    "physique-chimie": { "name": "Physique-Chimie", "det": "de", "color": "#B2B5D8" },
    "enseign.scientifique": { "name": "Enseignement Scientifique", "det": "d'", "color": "#B2B5D8" },

    "sciences de la vie et de la terre": { "name": "SVT", "det": "de", "color": "#9AC77E" },
    "sciences vie & terre": { "name": "SVT", "det": "de", "color": "#9AC77E" },

    "numerique sc.inform.": { "name": "NSI", "det": "de", "color": "#A6D9C4" },
    "sc.numeriq.technol.": { "name": "SNT", "det": "de", "color": "#A6D9C4" },

    "bloc 1 smdsi": { "name": "Bloc 1 Support et Mise à Disposition des Services Informatiques", "det": "de", "color": "#E2A7B8" },
    "bloc 2 sisr": { "name": "Bloc 2 Solutions d’Infrastructure, Systèmes et Réseaux", "det": "de", "color": "#E2A7B8" },
    "bloc 2 slam": { "name": "Bloc 2 Solutions Logicielles et Applications Métiers", "det": "de", "color": "#E2A7B8" },
    "bloc 3 tp": { "name": "Bloc 3 Travaux Pratiques", "det": "de", "color": "#E2A7B8" },
    "at. professionnalis.": { "name": "Atelier de Professionnalisation", "det": "d'", "color": "#E2A7B8" },

    "art plastique": { "name": "Art Plastique", "det": "d'", "color": "#E0C195" },
    "education musicale": { "name": "Éducation Musicale", "det": "d'", "color": "#E0C195" },

    "eps": { "name": "EPS", "det": "d'", "color": "#F0B36A" },
    "ed.physique & sport.": { "name": "EPS", "det": "d'", "color": "#F0B36A" },
    "education physique et sportive": { "name": "EPS", "det": "d'", "color": "#F0B36A" },

    "vie de classe": { "name": "Vie de Classe", "det": "de", "color": "#E0C195" },
    "accompagnemt. perso.": { "name": "Accompagnement Personnalisé", "det": "d'", "color": "#E0C195" },

    "cantine": { "name": "Cantine", "det": "de", "color": "#E0C195" }
}